{
    "vcs_paramclassrepository": [
        "vcs_paramclassrepository",
        "hEeZs",
        "module",
        1
    ],
    "_vcs_unit__3647009037": [
        "_vcs_unit__3647009037",
        "UNvww",
        "module",
        2
    ],
    "std": [
        "std",
        "reYIK",
        "module",
        3
    ],
    "uvm_pkg": [
        "uvm_pkg",
        "zr7M1",
        "module",
        4
    ],
    "_vcs_msglog": [
        "_vcs_msglog",
        "zQBzV",
        "module",
        5
    ],
    "uvm_custom_install_recording": [
        "uvm_custom_install_recording",
        "nhiwz",
        "module",
        6
    ],
    "pcs_tx_rm_dpi_pkg": [
        "pcs_tx_rm_dpi_pkg",
        "zTsPh",
        "module",
        7
    ],
    "pcs_if": [
        "pcs_if",
        "MDNfU",
        "module",
        8
    ],
    "top": [
        "top",
        "Emx8S",
        "module",
        9
    ],
    "...MASTER...": [
        "SIM",
        "amcQw",
        "module",
        10
    ]
}